fb_sapp-0.5.7.dist-info/licenses/LICENSE
sapp/__init__.py
sapp/analysis_output.py
sapp/bulk_saver.py
sapp/cli.py
sapp/cli_lib.py
sapp/context.py
sapp/db.py
sapp/db_support.py
sapp/decorators.py
sapp/errors.py
sapp/filesystem.py
sapp/filter.py
sapp/iterutil.py
sapp/json_cmd.py
sapp/json_diagnostics.py
sapp/lint.py
sapp/metrics_logger.py
sapp/models.py
sapp/operating_system.py
sapp/queries.py
sapp/sarif.py
sapp/sarif_types.py
sapp/sharded_files.py
sapp/source_location.py
sapp/trace_graph.py
sapp/trimmed_trace_graph.py
sapp/warning_messages.py
sapp/extensions/__init__.py
sapp/extensions/prompt_extension.py
sapp/pipeline/__init__.py
sapp/pipeline/add_features.py
sapp/pipeline/add_reverse_traces.py
sapp/pipeline/base_parser.py
sapp/pipeline/create_database.py
sapp/pipeline/database_saver.py
sapp/pipeline/issue_callable_filter.py
sapp/pipeline/issue_handle_filter.py
sapp/pipeline/mariana_trench_parser.py
sapp/pipeline/mariana_trench_parser_objects.py
sapp/pipeline/mark_partial_flows.py
sapp/pipeline/meta_run_issue_duplicate_filter.py
sapp/pipeline/model_generator.py
sapp/pipeline/parallel_parser.py
sapp/pipeline/propagate_context_to_leaf_frames.py
sapp/pipeline/propagate_extra_features_to_instances.py
sapp/pipeline/propagate_to_crtex_anchors.py
sapp/pipeline/pysa_taint_parser.py
sapp/pipeline/trim_trace_graph.py
sapp/pipeline/warning_code_filter.py
sapp/tests/__init__.py
sapp/tests/bulk_saver_test.py
sapp/tests/cli_test.py
sapp/tests/db_support_test.py
sapp/tests/decorators_test.py
sapp/tests/fake_object_generator.py
sapp/tests/filter_test.py
sapp/tests/iterutil_test.py
sapp/tests/primary_key_generator_test.py
sapp/ui/__init__.py
sapp/ui/filter_predicates.py
sapp/ui/filters.py
sapp/ui/interactive.py
sapp/ui/issues.py
sapp/ui/query_result.py
sapp/ui/run.py
sapp/ui/schema.py
sapp/ui/server.py
sapp/ui/trace.py
sapp/ui/typeahead.py
sapp/ui/frontend/build/asset-manifest.json
sapp/ui/frontend/build/favicon.svg
sapp/ui/frontend/build/index.html
sapp/ui/frontend/build/manifest.json
sapp/ui/frontend/build/robots.txt
fb_sapp-0.5.7.dist-info/METADATA
fb_sapp-0.5.7.dist-info/WHEEL
fb_sapp-0.5.7.dist-info/entry_points.txt
fb_sapp-0.5.7.dist-info/top_level.txt
fb_sapp-0.5.7.dist-info/RECORD
