Metadata-Version: 2.4
Name: fb-sapp
Version: 0.5.7
Summary: Static Analysis Post-Processor for processing taint analysis results.
Home-page: https://github.com/facebook/sapp
Author: Facebook
Maintainer-email: pyre@fb.com
License-File: LICENSE
Requires-Dist: click>=8.1.3
Requires-Dist: click-log>=0.4.0
Requires-Dist: Flask>=2.3.3
Requires-Dist: Flask-Cors>=3.0.10
Requires-Dist: Flask-GraphQL>=2.0.1
Requires-Dist: graphene<3.0
Requires-Dist: graphene-sqlalchemy<3,>=2.3.0
Requires-Dist: ipython<8.4.0
Requires-Dist: munch>=2.5.0
Requires-Dist: prompt-toolkit>=3.0.29
Requires-Dist: Pygments>=2.12.0
Requires-Dist: pyre-extensions>=0.0.30
Requires-Dist: SQLAlchemy>=1.4.50
Requires-Dist: traitlets<6,>=5.2.2.post1
Requires-Dist: typing-extensions<5,>=4.2.0
Requires-Dist: xxhash<4,>=3.0.0
Requires-Dist: zstandard>=0.17.0
Requires-Dist: Werkzeug>=2.3.7
Requires-Dist: psutil
Dynamic: author
Dynamic: description
Dynamic: description-content-type
Dynamic: home-page
Dynamic: license-file
Dynamic: maintainer-email
Dynamic: requires-dist
Dynamic: summary
